Schemas_ses/__init__.py
Schemas_ses/enumeration/__init__.py
Schemas_ses/enumeration/enums.py
Schemas_ses/models/BlackListToken.py
Schemas_ses/models/DTOModel.py
Schemas_ses/models/__init__.py
Schemas_ses/models/model.py
Schemas_ses/models/objectid.py
Schemas_ses/models/schools/ExamResullt.py
Schemas_ses/models/schools/FinancialData.py
Schemas_ses/models/schools/GeneralInfo.py
Schemas_ses/models/schools/IdAndLocation.py
Schemas_ses/models/schools/OfficeAndFurniture.py
Schemas_ses/models/schools/ParticipatorySchoolManagement.py
Schemas_ses/models/schools/SocioEnvironnement.py
Schemas_ses/models/schools/StudentsRecord.py
Schemas_ses/models/schools/TeachingAndLearningEquipment.py
Schemas_ses/models/schools/TeachingStaff.py
Schemas_ses/models/schools/__init__.py
Schemas_ses/models/schools/schools.py
Schemas_ses/models/schools/schools_schema.json
Schemas_ses/type/__init__.py
Schemas_ses/type/types.py
schemas_ses-0.3.15.dist-info/METADATA
schemas_ses-0.3.15.dist-info/WHEEL
schemas_ses-0.3.15.dist-info/RECORD
