Metadata-Version: 2.3
Name: schemas_ses
Version: 0.3.15
Summary: 
Author: machkouroke
Author-email: machkour20.mo1@gmail.com
Requires-Python: >=3.11,<4.0
Classifier: Programming Language :: Python :: 3
Classifier: Programming Language :: Python :: 3.11
Classifier: Programming Language :: Python :: 3.12
Classifier: Programming Language :: Python :: 3.13
Requires-Dist: fastapi (>=0.115.0,<0.116.0)
Requires-Dist: pydantic[email] (>=2.8.2,<3.0.0)
Requires-Dist: pymongo (>=4.10.1,<5.0.0)
